{"organization":"kodustech","repository":"kodus-ai","categories":["api","productivity","backend","ai"],"description":"Open source AI code reviews — just like your senior dev would do.","languages":["typescript"],"madeInBrazil":true,"message":"Deixe uma estrela pra mostrar seu carinho","name":"Kodus","url":"https://github.com/kodustech/kodus-ai","stats":{"license":"Other","stars":{"value":599,"label":"599"},"forks":{"value":48,"label":"48"},"issues":{"value":10,"label":"10"},"closedIssues":{"value":15,"label":"15"},"commits":"Última quarta-feira","contributors":{"value":11,"label":"11"},"repositoryDependents":{"value":0,"label":"0"},"score":770},"maintainers":[{"bio":"building Kodus","blog":"https://kodus.io","name":"Gabriel Malinosqui","username":"malinosqui"}],"updatedAt":"2025-10-03"}